<?xml version="1.0"?>
<!DOCTYPE hibernate-mapping PUBLIC "-//Hibernate/Hibernate Mapping DTD 3.0//EN"
"http://hibernate.sourceforge.net/hibernate-mapping-3.0.dtd">
<!-- Generated Apr 14, 2017 11:59:15 AM by Hibernate Tools 3.5.0.Final -->
<hibernate-mapping package="com.jyd.bms.bean">
	<class name="com.jyd.bms.bean.ContactInfo" table="cus_secondary_contact_info">
		<id name="id" type="int">
			<column name="id" />
			<generator class="identity" />
		</id>
		<property name="name" type="java.lang.String">
			<column name="name" />
		</property>
		<property name="relationship" type="java.lang.String">
			<column name="relationship" />
		</property>
		
		<property name="mobilephone" type="java.lang.String">
			<column name="mobilephone" />
		</property>
		
		<many-to-one name="customer" column="cus_id" 
		class="CustomerInfo" />

		<property name="remark" type="java.lang.String">
			<column name="remark" />
		</property>
		<property name="createDate" type="java.sql.Timestamp">
			<column name="create_date" />
		</property>
		<property name="updateDate" type="java.sql.Timestamp">
			<column name="update_date" />
		</property>
		<property name="createUser" type="java.lang.String">
			<column name="create_user" />
		</property>
		<property name="updateUser" type="java.lang.String">
			<column name="update_user" />
		</property>
		
	</class>
</hibernate-mapping>
